nn_cfnctl/__init__.py
nn_cfnctl/__main__.py
nn_cfnctl/deploy.py
nn_cfnctl/deployer.py
nn_cfnctl/exceptions.py
nn_cfnctl/execute.py
nn_cfnctl/main.py
nn_cfnctl/yamlhelper.py
nn_cfnctl-0.2.0.dist-info/entry_points.txt
nn_cfnctl-0.2.0.dist-info/LICENSE
nn_cfnctl-0.2.0.dist-info/WHEEL
nn_cfnctl-0.2.0.dist-info/METADATA
nn_cfnctl-0.2.0.dist-info/RECORD
