Metadata-Version: 2.1
Name: nn-cfnctl
Version: 0.2.0
Summary: CLI Tool for deploying CloudFormation using a YAML based config file for stack and parameter settings.
License: MIT
Author: Henrik Stanley Mortensen
Author-email: hsmx@novonordisk.com
Requires-Python: >=3.8,<4.0
Classifier: License :: OSI Approved :: MIT License
Classifier: Programming Language :: Python :: 3
Classifier: Programming Language :: Python :: 3.10
Classifier: Programming Language :: Python :: 3.8
Classifier: Programming Language :: Python :: 3.9
Requires-Dist: PyYAML (>=6.0,<7.0)
Requires-Dist: boto3 (>=1.20.39,<2.0.0)
Requires-Dist: typer[all] (>=0.4.0,<0.5.0)
